README.md
setup.py
pysting.egg-info/PKG-INFO
pysting.egg-info/SOURCES.txt
pysting.egg-info/dependency_links.txt
pysting.egg-info/entry_points.txt
pysting.egg-info/top_level.txt
sting/__init__.py
sting/__main__.py
sting/sting.py